{"commitInfo":{"timestamp":1752470195451,"operation":"MERGE","operationParameters":{"predicate":"[\"(driver_id#1260373 = driver_id#25)\"]","matchedPredicates":"[{\"actionType\":\"update\"}]","notMatchedPredicates":"[{\"actionType\":\"insert\"}]","notMatchedBySourcePredicates":"[]"},"readVersion":885,"isolationLevel":"Serializable","isBlindAppend":false,"operationMetrics":{"numTargetRowsCopied":"0","numTargetRowsDeleted":"0","numTargetFilesAdded":"1","numTargetBytesAdded":"2635","numTargetBytesRemoved":"2637","numTargetDeletionVectorsAdded":"0","numTargetRowsMatchedUpdated":"100","executionTimeMs":"1552","numTargetRowsInserted":"0","numTargetRowsMatchedDeleted":"0","numTargetDeletionVectorsUpdated":"0","scanTimeMs":"207","numTargetRowsUpdated":"100","numOutputRows":"100","numTargetDeletionVectorsRemoved":"0","numTargetRowsNotMatchedBySourceUpdated":"0","numTargetChangeFilesAdded":"0","numSourceRows":"100","numTargetFilesRemoved":"1","numTargetRowsNotMatchedBySourceDeleted":"0","rewriteTimeMs":"95"},"engineInfo":"Apache-Spark/3.5.1 Delta-Lake/3.1.0","txnId":"0794e6bd-a610-4c6b-bf68-1eb8c2b20981"}}
{"add":{"path":"part-00000-8ce98b87-9756-41a0-92f9-41223d7b8d13-c000.snappy.parquet","partitionValues":{},"size":2635,"modificationTime":1752470195449,"dataChange":true,"stats":"{\"numRecords\":100,\"minValues\":{\"driver_id\":0,\"driver_location\":821,\"event_time\":\"2025-07-14T10:46:33.694+05:30\"},\"maxValues\":{\"driver_id\":99,\"driver_location\":1811,\"event_time\":\"2025-07-14T10:46:33.694+05:30\"},\"nullCount\":{\"driver_id\":0,\"driver_location\":0,\"is_available\":0,\"event_time\":0}}"}}
{"remove":{"path":"part-00000-509d4a36-3e29-493c-8a56-2a9da48a3a33-c000.snappy.parquet","deletionTimestamp":1752470195450,"dataChange":true,"extendedFileMetadata":true,"partitionValues":{},"size":2637,"stats":"{\"numRecords\":100}"}}
