{"commitInfo":{"timestamp":1752469149723,"operation":"MERGE","operationParameters":{"predicate":"[\"(driver_id#934145 = driver_id#25)\"]","matchedPredicates":"[{\"actionType\":\"update\"}]","notMatchedPredicates":"[{\"actionType\":\"insert\"}]","notMatchedBySourcePredicates":"[]"},"readVersion":656,"isolationLevel":"Serializable","isBlindAppend":false,"operationMetrics":{"numTargetRowsCopied":"0","numTargetRowsDeleted":"0","numTargetFilesAdded":"1","numTargetBytesAdded":"2635","numTargetBytesRemoved":"2637","numTargetDeletionVectorsAdded":"0","numTargetRowsMatchedUpdated":"100","executionTimeMs":"1651","numTargetRowsInserted":"0","numTargetRowsMatchedDeleted":"0","numTargetDeletionVectorsUpdated":"0","scanTimeMs":"203","numTargetRowsUpdated":"100","numOutputRows":"100","numTargetDeletionVectorsRemoved":"0","numTargetRowsNotMatchedBySourceUpdated":"0","numTargetChangeFilesAdded":"0","numSourceRows":"100","numTargetFilesRemoved":"1","numTargetRowsNotMatchedBySourceDeleted":"0","rewriteTimeMs":"205"},"engineInfo":"Apache-Spark/3.5.1 Delta-Lake/3.1.0","txnId":"cef35c4a-52bc-46dc-8ef0-4e8abf0d6f5d"}}
{"add":{"path":"part-00000-9e23cb5c-65a6-4fad-b798-25aadeb66571-c000.snappy.parquet","partitionValues":{},"size":2635,"modificationTime":1752469149721,"dataChange":true,"stats":"{\"numRecords\":100,\"minValues\":{\"driver_id\":0,\"driver_location\":612,\"event_time\":\"2025-07-14T10:29:07.895+05:30\"},\"maxValues\":{\"driver_id\":99,\"driver_location\":1602,\"event_time\":\"2025-07-14T10:29:07.895+05:30\"},\"nullCount\":{\"driver_id\":0,\"driver_location\":0,\"is_available\":0,\"event_time\":0}}"}}
{"remove":{"path":"part-00000-7829715c-ab88-4f4e-91b4-190e04b7eec0-c000.snappy.parquet","deletionTimestamp":1752469149722,"dataChange":true,"extendedFileMetadata":true,"partitionValues":{},"size":2637,"stats":"{\"numRecords\":100}"}}
