{"commitInfo":{"timestamp":1752471961866,"operation":"MERGE","operationParameters":{"predicate":"[\"(driver_id#1797555 = driver_id#25)\"]","matchedPredicates":"[{\"actionType\":\"update\"}]","notMatchedPredicates":"[{\"actionType\":\"insert\"}]","notMatchedBySourcePredicates":"[]"},"readVersion":1262,"isolationLevel":"Serializable","isBlindAppend":false,"operationMetrics":{"numTargetRowsCopied":"0","numTargetRowsDeleted":"0","numTargetFilesAdded":"1","numTargetBytesAdded":"2568","numTargetBytesRemoved":"2593","numTargetDeletionVectorsAdded":"0","numTargetRowsMatchedUpdated":"100","executionTimeMs":"1591","numTargetRowsInserted":"0","numTargetRowsMatchedDeleted":"0","numTargetDeletionVectorsUpdated":"0","scanTimeMs":"203","numTargetRowsUpdated":"100","numOutputRows":"100","numTargetDeletionVectorsRemoved":"0","numTargetRowsNotMatchedBySourceUpdated":"0","numTargetChangeFilesAdded":"0","numSourceRows":"100","numTargetFilesRemoved":"1","numTargetRowsNotMatchedBySourceDeleted":"0","rewriteTimeMs":"155"},"engineInfo":"Apache-Spark/3.5.1 Delta-Lake/3.1.0","txnId":"48b7b1a4-bcec-49e1-9741-745cf669dc85"}}
{"add":{"path":"part-00000-affe07ff-7eee-432e-9edf-1947a13934e7-c000.snappy.parquet","partitionValues":{},"size":2568,"modificationTime":1752471961864,"dataChange":true,"stats":"{\"numRecords\":100,\"minValues\":{\"driver_id\":0,\"driver_location\":1174,\"event_time\":\"2025-07-14T11:16:00.071+05:30\"},\"maxValues\":{\"driver_id\":99,\"driver_location\":2164,\"event_time\":\"2025-07-14T11:16:00.071+05:30\"},\"nullCount\":{\"driver_id\":0,\"driver_location\":0,\"is_available\":0,\"event_time\":0}}"}}
{"remove":{"path":"part-00000-0ac1de02-63d8-4a26-965a-93ba8cf79370-c000.snappy.parquet","deletionTimestamp":1752471961865,"dataChange":true,"extendedFileMetadata":true,"partitionValues":{},"size":2593,"stats":"{\"numRecords\":100}"}}
