{"commitInfo":{"timestamp":1752467508803,"operation":"MERGE","operationParameters":{"predicate":"[\"(driver_id#426929 = driver_id#25)\"]","matchedPredicates":"[{\"actionType\":\"update\"}]","notMatchedPredicates":"[{\"actionType\":\"insert\"}]","notMatchedBySourcePredicates":"[]"},"readVersion":300,"isolationLevel":"Serializable","isBlindAppend":false,"operationMetrics":{"numTargetRowsCopied":"0","numTargetRowsDeleted":"0","numTargetFilesAdded":"1","numTargetBytesAdded":"2636","numTargetBytesRemoved":"2637","numTargetDeletionVectorsAdded":"0","numTargetRowsMatchedUpdated":"100","executionTimeMs":"1977","numTargetRowsInserted":"0","numTargetRowsMatchedDeleted":"0","numTargetDeletionVectorsUpdated":"0","scanTimeMs":"582","numTargetRowsUpdated":"100","numOutputRows":"100","numTargetDeletionVectorsRemoved":"0","numTargetRowsNotMatchedBySourceUpdated":"0","numTargetChangeFilesAdded":"0","numSourceRows":"100","numTargetFilesRemoved":"1","numTargetRowsNotMatchedBySourceDeleted":"0","rewriteTimeMs":"102"},"engineInfo":"Apache-Spark/3.5.1 Delta-Lake/3.1.0","txnId":"9b067a28-09fc-4636-9b14-2d7ca2df03da"}}
{"add":{"path":"part-00000-cdfcc0e7-6ceb-4707-8db3-74dea613c716-c000.snappy.parquet","partitionValues":{},"size":2636,"modificationTime":1752467508802,"dataChange":true,"stats":"{\"numRecords\":100,\"minValues\":{\"driver_id\":0,\"driver_location\":284,\"event_time\":\"2025-07-14T10:01:46.668+05:30\"},\"maxValues\":{\"driver_id\":99,\"driver_location\":1274,\"event_time\":\"2025-07-14T10:01:46.668+05:30\"},\"nullCount\":{\"driver_id\":0,\"driver_location\":0,\"is_available\":0,\"event_time\":0}}"}}
{"remove":{"path":"part-00000-4c6865eb-ed62-4420-9a77-7bd5ee6f224b-c000.snappy.parquet","deletionTimestamp":1752467508803,"dataChange":true,"extendedFileMetadata":true,"partitionValues":{},"size":2637,"stats":"{\"numRecords\":100}"}}
