{"commitInfo":{"timestamp":1752810782251,"operation":"MERGE","operationParameters":{"predicate":"[\"(driver_id#54626 = driver_id#25)\"]","matchedPredicates":"[{\"actionType\":\"update\"}]","notMatchedPredicates":"[{\"actionType\":\"insert\"}]","notMatchedBySourcePredicates":"[]"},"readVersion":39,"isolationLevel":"Serializable","isBlindAppend":false,"operationMetrics":{"numTargetRowsCopied":"0","numTargetRowsDeleted":"0","numTargetFilesAdded":"1","numTargetBytesAdded":"2634","numTargetBytesRemoved":"2635","numTargetDeletionVectorsAdded":"0","numTargetRowsMatchedUpdated":"100","executionTimeMs":"1617","numTargetRowsInserted":"0","numTargetRowsMatchedDeleted":"0","numTargetDeletionVectorsUpdated":"0","scanTimeMs":"247","numTargetRowsUpdated":"100","numOutputRows":"100","numTargetDeletionVectorsRemoved":"0","numTargetRowsNotMatchedBySourceUpdated":"0","numTargetChangeFilesAdded":"0","numSourceRows":"100","numTargetFilesRemoved":"1","numTargetRowsNotMatchedBySourceDeleted":"0","rewriteTimeMs":"131"},"engineInfo":"Apache-Spark/3.5.1 Delta-Lake/3.1.0","txnId":"f35d0e4e-2aae-4b3c-a615-ee6878968215"}}
{"add":{"path":"part-00000-4d741478-ff35-4eb9-a1e6-a7533de715d3-c000.snappy.parquet","partitionValues":{},"size":2634,"modificationTime":1752810782249,"dataChange":true,"stats":"{\"numRecords\":100,\"minValues\":{\"driver_id\":0,\"driver_location\":43,\"event_time\":\"2025-07-18T09:23:00.567+05:30\"},\"maxValues\":{\"driver_id\":99,\"driver_location\":1033,\"event_time\":\"2025-07-18T09:23:00.568+05:30\"},\"nullCount\":{\"driver_id\":0,\"driver_location\":0,\"is_available\":0,\"event_time\":0}}"}}
{"remove":{"path":"part-00000-9907ecbc-2183-4e4b-8cc5-8267b0819224-c000.snappy.parquet","deletionTimestamp":1752810782251,"dataChange":true,"extendedFileMetadata":true,"partitionValues":{},"size":2635,"stats":"{\"numRecords\":100}"}}
