{"commitInfo":{"timestamp":1752471236279,"operation":"MERGE","operationParameters":{"predicate":"[\"(driver_id#1579049 = driver_id#25)\"]","matchedPredicates":"[{\"actionType\":\"update\"}]","notMatchedPredicates":"[{\"actionType\":\"insert\"}]","notMatchedBySourcePredicates":"[]"},"readVersion":1109,"isolationLevel":"Serializable","isBlindAppend":false,"operationMetrics":{"numTargetRowsCopied":"83","numTargetRowsDeleted":"0","numTargetFilesAdded":"1","numTargetBytesAdded":"2427","numTargetBytesRemoved":"2347","numTargetDeletionVectorsAdded":"0","numTargetRowsMatchedUpdated":"17","executionTimeMs":"1557","numTargetRowsInserted":"0","numTargetRowsMatchedDeleted":"0","numTargetDeletionVectorsUpdated":"0","scanTimeMs":"195","numTargetRowsUpdated":"17","numOutputRows":"100","numTargetDeletionVectorsRemoved":"0","numTargetRowsNotMatchedBySourceUpdated":"0","numTargetChangeFilesAdded":"0","numSourceRows":"17","numTargetFilesRemoved":"1","numTargetRowsNotMatchedBySourceDeleted":"0","rewriteTimeMs":"146"},"engineInfo":"Apache-Spark/3.5.1 Delta-Lake/3.1.0","txnId":"c904c42c-8d08-4d2e-8411-5ad3e80d73b4"}}
{"add":{"path":"part-00000-d920ded7-7da6-459d-a7ba-499a002ed541-c000.snappy.parquet","partitionValues":{},"size":2427,"modificationTime":1752471236278,"dataChange":true,"stats":"{\"numRecords\":100,\"minValues\":{\"driver_id\":0,\"driver_location\":1028,\"event_time\":\"2025-07-14T11:03:49.522+05:30\"},\"maxValues\":{\"driver_id\":99,\"driver_location\":2018,\"event_time\":\"2025-07-14T11:03:54.527+05:30\"},\"nullCount\":{\"driver_id\":0,\"driver_location\":0,\"is_available\":0,\"event_time\":0}}"}}
{"remove":{"path":"part-00000-b436d867-5654-4395-a43f-68dcb375286b-c000.snappy.parquet","deletionTimestamp":1752471236279,"dataChange":true,"extendedFileMetadata":true,"partitionValues":{},"size":2347,"stats":"{\"numRecords\":100}"}}
