{"commitInfo":{"timestamp":1752468894472,"operation":"MERGE","operationParameters":{"predicate":"[\"(driver_id#852707 = driver_id#25)\"]","matchedPredicates":"[{\"actionType\":\"update\"}]","notMatchedPredicates":"[{\"actionType\":\"insert\"}]","notMatchedBySourcePredicates":"[]"},"readVersion":599,"isolationLevel":"Serializable","isBlindAppend":false,"operationMetrics":{"numTargetRowsCopied":"0","numTargetRowsDeleted":"0","numTargetFilesAdded":"1","numTargetBytesAdded":"2330","numTargetBytesRemoved":"2636","numTargetDeletionVectorsAdded":"0","numTargetRowsMatchedUpdated":"100","executionTimeMs":"1673","numTargetRowsInserted":"0","numTargetRowsMatchedDeleted":"0","numTargetDeletionVectorsUpdated":"0","scanTimeMs":"201","numTargetRowsUpdated":"100","numOutputRows":"100","numTargetDeletionVectorsRemoved":"0","numTargetRowsNotMatchedBySourceUpdated":"0","numTargetChangeFilesAdded":"0","numSourceRows":"100","numTargetFilesRemoved":"1","numTargetRowsNotMatchedBySourceDeleted":"0","rewriteTimeMs":"207"},"engineInfo":"Apache-Spark/3.5.1 Delta-Lake/3.1.0","txnId":"3578bdff-cef3-40b2-b66b-bb679a37906d"}}
{"add":{"path":"part-00000-ada50eb9-1e31-41bc-bc32-92d47d3137da-c000.snappy.parquet","partitionValues":{},"size":2330,"modificationTime":1752468894470,"dataChange":true,"stats":"{\"numRecords\":100,\"minValues\":{\"driver_id\":0,\"driver_location\":561,\"event_time\":\"2025-07-14T10:24:52.702+05:30\"},\"maxValues\":{\"driver_id\":99,\"driver_location\":1551,\"event_time\":\"2025-07-14T10:24:52.702+05:30\"},\"nullCount\":{\"driver_id\":0,\"driver_location\":0,\"is_available\":0,\"event_time\":0}}"}}
{"remove":{"path":"part-00000-92305a61-1896-42b0-90c0-a898a22d34dc-c000.snappy.parquet","deletionTimestamp":1752468894471,"dataChange":true,"extendedFileMetadata":true,"partitionValues":{},"size":2636,"stats":"{\"numRecords\":100}"}}
