{"commitInfo":{"timestamp":1752470350674,"operation":"MERGE","operationParameters":{"predicate":"[\"(driver_id#1308451 = driver_id#25)\"]","matchedPredicates":"[{\"actionType\":\"update\"}]","notMatchedPredicates":"[{\"actionType\":\"insert\"}]","notMatchedBySourcePredicates":"[]"},"readVersion":919,"isolationLevel":"Serializable","isBlindAppend":false,"operationMetrics":{"numTargetRowsCopied":"8","numTargetRowsDeleted":"0","numTargetFilesAdded":"1","numTargetBytesAdded":"2635","numTargetBytesRemoved":"2636","numTargetDeletionVectorsAdded":"0","numTargetRowsMatchedUpdated":"92","executionTimeMs":"1679","numTargetRowsInserted":"0","numTargetRowsMatchedDeleted":"0","numTargetDeletionVectorsUpdated":"0","scanTimeMs":"226","numTargetRowsUpdated":"92","numOutputRows":"100","numTargetDeletionVectorsRemoved":"0","numTargetRowsNotMatchedBySourceUpdated":"0","numTargetChangeFilesAdded":"0","numSourceRows":"92","numTargetFilesRemoved":"1","numTargetRowsNotMatchedBySourceDeleted":"0","rewriteTimeMs":"188"},"engineInfo":"Apache-Spark/3.5.1 Delta-Lake/3.1.0","txnId":"a6e3142c-fac6-4612-b548-e5d0fc68bf74"}}
{"add":{"path":"part-00000-66afafd7-4dc1-4494-8bd6-4bd193dacd7f-c000.snappy.parquet","partitionValues":{},"size":2635,"modificationTime":1752470350672,"dataChange":true,"stats":"{\"numRecords\":100,\"minValues\":{\"driver_id\":0,\"driver_location\":852,\"event_time\":\"2025-07-14T10:49:03.811+05:30\"},\"maxValues\":{\"driver_id\":99,\"driver_location\":1841,\"event_time\":\"2025-07-14T10:49:08.814+05:30\"},\"nullCount\":{\"driver_id\":0,\"driver_location\":0,\"is_available\":0,\"event_time\":0}}"}}
{"remove":{"path":"part-00000-9454d59d-23dc-414c-a0e8-f52901b57838-c000.snappy.parquet","deletionTimestamp":1752470350673,"dataChange":true,"extendedFileMetadata":true,"partitionValues":{},"size":2636,"stats":"{\"numRecords\":100}"}}
