{"commitInfo":{"timestamp":1752468699311,"operation":"MERGE","operationParameters":{"predicate":"[\"(driver_id#791725 = driver_id#25)\"]","matchedPredicates":"[{\"actionType\":\"update\"}]","notMatchedPredicates":"[{\"actionType\":\"insert\"}]","notMatchedBySourcePredicates":"[]"},"readVersion":556,"isolationLevel":"Serializable","isBlindAppend":false,"operationMetrics":{"numTargetRowsCopied":"0","numTargetRowsDeleted":"0","numTargetFilesAdded":"1","numTargetBytesAdded":"2297","numTargetBytesRemoved":"2635","numTargetDeletionVectorsAdded":"0","numTargetRowsMatchedUpdated":"100","executionTimeMs":"1661","numTargetRowsInserted":"0","numTargetRowsMatchedDeleted":"0","numTargetDeletionVectorsUpdated":"0","scanTimeMs":"226","numTargetRowsUpdated":"100","numOutputRows":"100","numTargetDeletionVectorsRemoved":"0","numTargetRowsNotMatchedBySourceUpdated":"0","numTargetChangeFilesAdded":"0","numSourceRows":"100","numTargetFilesRemoved":"1","numTargetRowsNotMatchedBySourceDeleted":"0","rewriteTimeMs":"203"},"engineInfo":"Apache-Spark/3.5.1 Delta-Lake/3.1.0","txnId":"473bd178-1d26-4c8b-9831-b8e3dcb0e39c"}}
{"add":{"path":"part-00000-310383e4-8a96-4278-baf4-3e6db71bde75-c000.snappy.parquet","partitionValues":{},"size":2297,"modificationTime":1752468699309,"dataChange":true,"stats":"{\"numRecords\":100,\"minValues\":{\"driver_id\":0,\"driver_location\":522,\"event_time\":\"2025-07-14T10:21:37.549+05:30\"},\"maxValues\":{\"driver_id\":99,\"driver_location\":1512,\"event_time\":\"2025-07-14T10:21:37.549+05:30\"},\"nullCount\":{\"driver_id\":0,\"driver_location\":0,\"is_available\":0,\"event_time\":0}}"}}
{"remove":{"path":"part-00000-cdeadff3-2f32-42e9-abaa-39f5f2896a49-c000.snappy.parquet","deletionTimestamp":1752468699311,"dataChange":true,"extendedFileMetadata":true,"partitionValues":{},"size":2635,"stats":"{\"numRecords\":100}"}}
