{"commitInfo":{"timestamp":1752466577517,"operation":"MERGE","operationParameters":{"predicate":"[\"(driver_id#145483 = driver_id#25)\"]","matchedPredicates":"[{\"actionType\":\"update\"}]","notMatchedPredicates":"[{\"actionType\":\"insert\"}]","notMatchedBySourcePredicates":"[]"},"readVersion":102,"isolationLevel":"Serializable","isBlindAppend":false,"operationMetrics":{"numTargetRowsCopied":"0","numTargetRowsDeleted":"0","numTargetFilesAdded":"1","numTargetBytesAdded":"2635","numTargetBytesRemoved":"2634","numTargetDeletionVectorsAdded":"0","numTargetRowsMatchedUpdated":"100","executionTimeMs":"1533","numTargetRowsInserted":"0","numTargetRowsMatchedDeleted":"0","numTargetDeletionVectorsUpdated":"0","scanTimeMs":"201","numTargetRowsUpdated":"100","numOutputRows":"100","numTargetDeletionVectorsRemoved":"0","numTargetRowsNotMatchedBySourceUpdated":"0","numTargetChangeFilesAdded":"0","numSourceRows":"100","numTargetFilesRemoved":"1","numTargetRowsNotMatchedBySourceDeleted":"0","rewriteTimeMs":"93"},"engineInfo":"Apache-Spark/3.5.1 Delta-Lake/3.1.0","txnId":"481b7b1c-1475-44fb-a0f0-08c106d5ec06"}}
{"add":{"path":"part-00000-c6be9353-3322-4379-af83-bff6ff0fee5b-c000.snappy.parquet","partitionValues":{},"size":2635,"modificationTime":1752466577515,"dataChange":true,"stats":"{\"numRecords\":100,\"minValues\":{\"driver_id\":0,\"driver_location\":98,\"event_time\":\"2025-07-14T09:46:15.892+05:30\"},\"maxValues\":{\"driver_id\":99,\"driver_location\":1088,\"event_time\":\"2025-07-14T09:46:15.893+05:30\"},\"nullCount\":{\"driver_id\":0,\"driver_location\":0,\"is_available\":0,\"event_time\":0}}"}}
{"remove":{"path":"part-00000-4d94f271-a8bc-46e6-9f8e-eb699cf90d59-c000.snappy.parquet","deletionTimestamp":1752466577517,"dataChange":true,"extendedFileMetadata":true,"partitionValues":{},"size":2634,"stats":"{\"numRecords\":100}"}}
