{"commitInfo":{"timestamp":1752470352771,"operation":"MERGE","operationParameters":{"predicate":"[\"(driver_id#1309933 = driver_id#25)\"]","matchedPredicates":"[{\"actionType\":\"update\"}]","notMatchedPredicates":"[{\"actionType\":\"insert\"}]","notMatchedBySourcePredicates":"[]"},"readVersion":920,"isolationLevel":"Serializable","isBlindAppend":false,"operationMetrics":{"numTargetRowsCopied":"92","numTargetRowsDeleted":"0","numTargetFilesAdded":"1","numTargetBytesAdded":"2635","numTargetBytesRemoved":"2635","numTargetDeletionVectorsAdded":"0","numTargetRowsMatchedUpdated":"8","executionTimeMs":"921","numTargetRowsInserted":"0","numTargetRowsMatchedDeleted":"0","numTargetDeletionVectorsUpdated":"0","scanTimeMs":"459","numTargetRowsUpdated":"8","numOutputRows":"100","numTargetDeletionVectorsRemoved":"0","numTargetRowsNotMatchedBySourceUpdated":"0","numTargetChangeFilesAdded":"0","numSourceRows":"8","numTargetFilesRemoved":"1","numTargetRowsNotMatchedBySourceDeleted":"0","rewriteTimeMs":"379"},"engineInfo":"Apache-Spark/3.5.1 Delta-Lake/3.1.0","txnId":"8dd56337-2489-4dbd-8da5-aaa9606fdb74"}}
{"add":{"path":"part-00000-97405d6e-5dfc-4563-88b4-b9551757e60d-c000.snappy.parquet","partitionValues":{},"size":2635,"modificationTime":1752470352769,"dataChange":true,"stats":"{\"numRecords\":100,\"minValues\":{\"driver_id\":0,\"driver_location\":852,\"event_time\":\"2025-07-14T10:49:08.813+05:30\"},\"maxValues\":{\"driver_id\":99,\"driver_location\":1842,\"event_time\":\"2025-07-14T10:49:08.814+05:30\"},\"nullCount\":{\"driver_id\":0,\"driver_location\":0,\"is_available\":0,\"event_time\":0}}"}}
{"remove":{"path":"part-00000-66afafd7-4dc1-4494-8bd6-4bd193dacd7f-c000.snappy.parquet","deletionTimestamp":1752470352770,"dataChange":true,"extendedFileMetadata":true,"partitionValues":{},"size":2635,"stats":"{\"numRecords\":100}"}}
