{"commitInfo":{"timestamp":1752469089497,"operation":"MERGE","operationParameters":{"predicate":"[\"(driver_id#915889 = driver_id#25)\"]","matchedPredicates":"[{\"actionType\":\"update\"}]","notMatchedPredicates":"[{\"actionType\":\"insert\"}]","notMatchedBySourcePredicates":"[]"},"readVersion":643,"isolationLevel":"Serializable","isBlindAppend":false,"operationMetrics":{"numTargetRowsCopied":"0","numTargetRowsDeleted":"0","numTargetFilesAdded":"1","numTargetBytesAdded":"2338","numTargetBytesRemoved":"2639","numTargetDeletionVectorsAdded":"0","numTargetRowsMatchedUpdated":"100","executionTimeMs":"1544","numTargetRowsInserted":"0","numTargetRowsMatchedDeleted":"0","numTargetDeletionVectorsUpdated":"0","scanTimeMs":"163","numTargetRowsUpdated":"100","numOutputRows":"100","numTargetDeletionVectorsRemoved":"0","numTargetRowsNotMatchedBySourceUpdated":"0","numTargetChangeFilesAdded":"0","numSourceRows":"100","numTargetFilesRemoved":"1","numTargetRowsNotMatchedBySourceDeleted":"0","rewriteTimeMs":"187"},"engineInfo":"Apache-Spark/3.5.1 Delta-Lake/3.1.0","txnId":"87cb46b9-35da-4a01-a168-5e5600bc80e6"}}
{"add":{"path":"part-00000-cbefddbf-502c-4b3c-879e-1e4582b05dac-c000.snappy.parquet","partitionValues":{},"size":2338,"modificationTime":1752469089496,"dataChange":true,"stats":"{\"numRecords\":100,\"minValues\":{\"driver_id\":0,\"driver_location\":600,\"event_time\":\"2025-07-14T10:28:07.848+05:30\"},\"maxValues\":{\"driver_id\":99,\"driver_location\":1590,\"event_time\":\"2025-07-14T10:28:07.848+05:30\"},\"nullCount\":{\"driver_id\":0,\"driver_location\":0,\"is_available\":0,\"event_time\":0}}"}}
{"remove":{"path":"part-00000-56a66b95-f251-4d12-a6ea-27c89dbcea0d-c000.snappy.parquet","deletionTimestamp":1752469089497,"dataChange":true,"extendedFileMetadata":true,"partitionValues":{},"size":2639,"stats":"{\"numRecords\":100}"}}
