{"commitInfo":{"timestamp":1752469960287,"operation":"MERGE","operationParameters":{"predicate":"[\"(driver_id#1186487 = driver_id#25)\"]","matchedPredicates":"[{\"actionType\":\"update\"}]","notMatchedPredicates":"[{\"actionType\":\"insert\"}]","notMatchedBySourcePredicates":"[]"},"readVersion":833,"isolationLevel":"Serializable","isBlindAppend":false,"operationMetrics":{"numTargetRowsCopied":"15","numTargetRowsDeleted":"0","numTargetFilesAdded":"1","numTargetBytesAdded":"2640","numTargetBytesRemoved":"2635","numTargetDeletionVectorsAdded":"0","numTargetRowsMatchedUpdated":"85","executionTimeMs":"1589","numTargetRowsInserted":"0","numTargetRowsMatchedDeleted":"0","numTargetDeletionVectorsUpdated":"0","scanTimeMs":"232","numTargetRowsUpdated":"85","numOutputRows":"100","numTargetDeletionVectorsRemoved":"0","numTargetRowsNotMatchedBySourceUpdated":"0","numTargetChangeFilesAdded":"0","numSourceRows":"85","numTargetFilesRemoved":"1","numTargetRowsNotMatchedBySourceDeleted":"0","rewriteTimeMs":"112"},"engineInfo":"Apache-Spark/3.5.1 Delta-Lake/3.1.0","txnId":"d4779864-c0d5-4878-86c2-e4fc3eab3a2b"}}
{"add":{"path":"part-00000-4dd056ce-e92f-4789-bd34-22d5c7660b8b-c000.snappy.parquet","partitionValues":{},"size":2640,"modificationTime":1752469960285,"dataChange":true,"stats":"{\"numRecords\":100,\"minValues\":{\"driver_id\":0,\"driver_location\":774,\"event_time\":\"2025-07-14T10:42:33.505+05:30\"},\"maxValues\":{\"driver_id\":99,\"driver_location\":1763,\"event_time\":\"2025-07-14T10:42:38.510+05:30\"},\"nullCount\":{\"driver_id\":0,\"driver_location\":0,\"is_available\":0,\"event_time\":0}}"}}
{"remove":{"path":"part-00000-079ab764-7786-4246-94fc-77afdbc8986c-c000.snappy.parquet","deletionTimestamp":1752469960287,"dataChange":true,"extendedFileMetadata":true,"partitionValues":{},"size":2635,"stats":"{\"numRecords\":100}"}}
