{"commitInfo":{"timestamp":1752468874475,"operation":"MERGE","operationParameters":{"predicate":"[\"(driver_id#846017 = driver_id#25)\"]","matchedPredicates":"[{\"actionType\":\"update\"}]","notMatchedPredicates":"[{\"actionType\":\"insert\"}]","notMatchedBySourcePredicates":"[]"},"readVersion":594,"isolationLevel":"Serializable","isBlindAppend":false,"operationMetrics":{"numTargetRowsCopied":"0","numTargetRowsDeleted":"0","numTargetFilesAdded":"1","numTargetBytesAdded":"2641","numTargetBytesRemoved":"2637","numTargetDeletionVectorsAdded":"0","numTargetRowsMatchedUpdated":"100","executionTimeMs":"1602","numTargetRowsInserted":"0","numTargetRowsMatchedDeleted":"0","numTargetDeletionVectorsUpdated":"0","scanTimeMs":"188","numTargetRowsUpdated":"100","numOutputRows":"100","numTargetDeletionVectorsRemoved":"0","numTargetRowsNotMatchedBySourceUpdated":"0","numTargetChangeFilesAdded":"0","numSourceRows":"100","numTargetFilesRemoved":"1","numTargetRowsNotMatchedBySourceDeleted":"0","rewriteTimeMs":"182"},"engineInfo":"Apache-Spark/3.5.1 Delta-Lake/3.1.0","txnId":"eea43ab4-371c-4f5e-8a49-f842de4fbd10"}}
{"add":{"path":"part-00000-bc7ed445-57f5-4385-ae3b-4ba21407ff7b-c000.snappy.parquet","partitionValues":{},"size":2641,"modificationTime":1752468874474,"dataChange":true,"stats":"{\"numRecords\":100,\"minValues\":{\"driver_id\":0,\"driver_location\":557,\"event_time\":\"2025-07-14T10:24:32.682+05:30\"},\"maxValues\":{\"driver_id\":99,\"driver_location\":1547,\"event_time\":\"2025-07-14T10:24:32.683+05:30\"},\"nullCount\":{\"driver_id\":0,\"driver_location\":0,\"is_available\":0,\"event_time\":0}}"}}
{"remove":{"path":"part-00000-e7e2bfb2-7486-4fcd-8d9d-b43e26dec850-c000.snappy.parquet","deletionTimestamp":1752468874475,"dataChange":true,"extendedFileMetadata":true,"partitionValues":{},"size":2637,"stats":"{\"numRecords\":100}"}}
